{
  "run_metadata": {
    "run_id": "BL011-CTRL-20260325-020828",
    "task": "BL-011",
    "generated_at_utc": "2026-03-25T02:09:28Z",
    "elapsed_seconds": 59.573,
    "baseline_config_hash": "4C6934E266AD3E572562CC2115CEDF2F1D8AAE16E4DE9D8E89E442ED3A46C0CB",
    "scenario_count": 5
  },
  "inputs": {
    "baseline_snapshot_path": "07_implementation/implementation_notes/reproducibility/outputs/bl010_reproducibility_config_snapshot.json",
    "controllability_config_snapshot_path": "07_implementation/implementation_notes/controllability/outputs/bl011_controllability_config_snapshot.json",
    "fixed_input_hashes": {
      "07_implementation/implementation_notes/profile/outputs/bl004_seed_trace.csv": "6378F963A43ADAACE2818945E1F5216323D1880853085446FDB74D00CD7B525C",
      "07_implementation/implementation_notes/data_layer/outputs/ds001_working_candidate_dataset.csv": "296331CA6390D2C111AA336C7EB154B69EC7060604312AC8A274F545B68A04EF"
    }
  },
  "scope": {
    "evaluation_tests": [
      "EP-CTRL-001",
      "EP-CTRL-002",
      "EP-CTRL-003"
    ],
    "scenario_ids": [
      "baseline",
      "no_influence_tracks",
      "valence_weight_up",
      "stricter_thresholds",
      "looser_thresholds"
    ],
    "stage_scope": [
      "BL-004",
      "BL-005",
      "BL-006",
      "BL-007"
    ],
    "repeat_method": "each scenario was executed twice with identical parameters and compared via stable stage hashes"
  },
  "scenario_results": [
    {
      "scenario_id": "baseline",
      "test_id": "baseline",
      "control_surface": "fixed_bl010_baseline",
      "description": "BL-010 fixed baseline carried forward unchanged for BL-011 comparisons.",
      "expected_effect": "reference",
      "repeat_consistent": true,
      "config_hash": "B00DCC043F2FA748D580CC2D2C96546BD26315F13E205AF6F39EBE125233A4DC",
      "effective_config": {
        "scenario_id": "baseline",
        "test_id": "baseline",
        "control_surface": "fixed_bl010_baseline",
        "description": "BL-010 fixed baseline carried forward unchanged for BL-011 comparisons.",
        "expected_effect": "reference",
        "profile": {
          "effective_weight_rule": "effective_weight = preference_weight",
          "numeric_feature_columns": [
            "danceability",
            "energy",
            "valence",
            "tempo",
            "key",
            "mode",
            "popularity",
            "duration_ms"
          ],
          "top_tag_limit": 10,
          "top_genre_limit": 10,
          "top_lead_genre_limit": 10,
          "aggregation_rules": {
            "numeric": "weighted mean over numeric columns embedded in the BL-003 enriched seed table; key uses weighted circular mean on the 12-semitone wheel",
            "tags": "sum(preference_weight) over DS-001 tag labels",
            "genres": "sum(preference_weight) over DS-001 genre labels",
            "lead_genres": "sum(preference_weight)"
          },
          "include_interaction_types": [
            "history",
            "influence"
          ]
        },
        "retrieval": {
          "top_lead_genre_limit": 6,
          "top_tag_limit": 10,
          "top_genre_limit": 8,
          "threshold_scale": 1.0,
          "numeric_thresholds": {
            "tempo": 20.0,
            "key": 2.0,
            "mode": 0.5,
            "duration_ms": 45000.0
          },
          "keep_rule": "keep if not seed and (semantic_score >= 2 or (semantic_score >= 1 and numeric_pass_count >= 1))"
        },
        "scoring": {
          "numeric_thresholds": {
            "tempo": 20.0,
            "key": 2.0,
            "mode": 0.5,
            "duration_ms": 45000.0
          },
          "component_weights": {
            "tempo": 0.2,
            "duration_ms": 0.13,
            "key": 0.13,
            "mode": 0.09,
            "lead_genre": 0.17,
            "genre_overlap": 0.12,
            "tag_overlap": 0.16
          },
          "weight_override_component": null,
          "raw_override_value": null
        },
        "assembly": {
          "target_size": 10,
          "min_score_threshold": 0.35,
          "max_per_genre": 4,
          "max_consecutive": 2
        }
      },
      "stable_hashes": {
        "profile_semantic_hash": "783BE37C440FAF30FC81CABB6605049DE088FBEC87A9FCE2840F64254B192372",
        "seed_trace_hash": "7896232795DF347E426EEE2F5346BAA1A776F445FEBCA08B95FAFF1B884A1C7E",
        "filtered_candidates_hash": "D160E6B2FE3E13BC9E0EB8D430A67580CAFEBBB82AE37BAB332928C32A25C0A5",
        "candidate_decisions_hash": "54E4F14F1BEFCA6163671CA121B94CEFF5AE0E1E43B2B4A176D195F46F025B24",
        "ranked_output_hash": "D0764BA430A44E797A6D02D5D3F1EB5D8D8FC3CF4CA22C21D4C2A6173D1835A8",
        "assembly_trace_hash": "0B2EF977EB376DB44353DD9B549EC74B4E0C50DDF2F19B4FEBA2CA1DD6E43201",
        "playlist_output_hash": "D16015CFA1AC70E93A22F798E713BC14C6ED27617B7715715429842CF312D038"
      },
      "metrics": {
        "selected_event_count": 1563,
        "matched_seed_count": 1563,
        "candidate_pool_size": 56691,
        "scored_candidate_count": 56691,
        "playlist_length": 10,
        "top10_track_ids": [
          "CaR8UnowNJUR5Dib",
          "yEz9rqTTulkiDDm7",
          "M3ApGs7RGZwXHqs4",
          "rqeIltq5ixzHA5EG",
          "s0Qo4gihN9Rzx8we",
          "qob8Z8qGt0UR4JAs",
          "Xh9f0R2Q7wJMaxhy",
          "HheoXQPQtBis2mmJ",
          "M1aGgogF0dGiRiXA",
          "YEWH2dMDiRCIJy7F"
        ],
        "playlist_track_ids": [
          "CaR8UnowNJUR5Dib",
          "yEz9rqTTulkiDDm7",
          "M3ApGs7RGZwXHqs4",
          "rqeIltq5ixzHA5EG",
          "s0Qo4gihN9Rzx8we",
          "qob8Z8qGt0UR4JAs",
          "Xh9f0R2Q7wJMaxhy",
          "HheoXQPQtBis2mmJ",
          "M1aGgogF0dGiRiXA",
          "CZOYJJKuyuUosACw"
        ],
        "dominant_lead_genres": [
          "pop",
          "classic rock",
          "rock",
          "progressive rock",
          "new wave"
        ],
        "dominant_tags": [
          "rock",
          "classic rock",
          "pop",
          "80s",
          "70s"
        ],
        "mean_component_contributions": {
          "tempo": 0.056181,
          "duration_ms": 0.030051,
          "key": 0.020326,
          "mode": 0.024535,
          "lead_genre": 0.045727,
          "genre_overlap": 0.027141,
          "tag_overlap": 0.03098
        },
        "playlist_genre_mix": {
          "classic rock": 4,
          "pop": 4,
          "rock": 2
        }
      },
      "comparison_to_baseline": {
        "observable_shift": false,
        "expected_direction_met": true,
        "candidate_pool_size_delta": 0,
        "playlist_length_delta": 0,
        "top10_overlap_count": 10,
        "top10_overlap_ratio": 1.0,
        "playlist_overlap_count": 10,
        "playlist_overlap_ratio": 1.0,
        "top10_added_track_ids": [],
        "top10_removed_track_ids": [],
        "playlist_added_track_ids": [],
        "playlist_removed_track_ids": [],
        "profile_lead_genres_before": [
          "pop",
          "classic rock",
          "rock",
          "progressive rock",
          "new wave"
        ],
        "profile_lead_genres_after": [
          "pop",
          "classic rock",
          "rock",
          "progressive rock",
          "new wave"
        ],
        "component_mean_delta": {
          "tempo": 0.0,
          "duration_ms": 0.0,
          "key": 0.0,
          "mode": 0.0,
          "lead_genre": 0.0,
          "genre_overlap": 0.0,
          "tag_overlap": 0.0
        },
        "rank_shift_summary": {
          "common_candidate_count": 56691,
          "mean_abs_rank_delta": 0.0,
          "max_rank_improvement": 0,
          "max_rank_drop": 0,
          "top_risers": [],
          "top_fallers": []
        }
      },
      "archive_dir": "07_implementation/implementation_notes/controllability/outputs/scenarios/baseline"
    },
    {
      "scenario_id": "no_influence_tracks",
      "test_id": "EP-CTRL-001",
      "control_surface": "influence_tracks",
      "description": "Disable influence-track interactions while keeping all other inputs and parameters fixed.",
      "expected_effect": "profile and ranking shift away from influence-steered indie/alternative emphasis",
      "repeat_consistent": true,
      "config_hash": "16F62C32689E526A808AD3EB4A319388B28F267B3DD154B9AD5E5616F178F96E",
      "effective_config": {
        "scenario_id": "no_influence_tracks",
        "test_id": "EP-CTRL-001",
        "control_surface": "influence_tracks",
        "description": "Disable influence-track interactions while keeping all other inputs and parameters fixed.",
        "expected_effect": "profile and ranking shift away from influence-steered indie/alternative emphasis",
        "profile": {
          "effective_weight_rule": "effective_weight = preference_weight",
          "numeric_feature_columns": [
            "danceability",
            "energy",
            "valence",
            "tempo",
            "key",
            "mode",
            "popularity",
            "duration_ms"
          ],
          "top_tag_limit": 10,
          "top_genre_limit": 10,
          "top_lead_genre_limit": 10,
          "aggregation_rules": {
            "numeric": "weighted mean over numeric columns embedded in the BL-003 enriched seed table; key uses weighted circular mean on the 12-semitone wheel",
            "tags": "sum(preference_weight) over DS-001 tag labels",
            "genres": "sum(preference_weight) over DS-001 genre labels",
            "lead_genres": "sum(preference_weight)"
          },
          "include_interaction_types": [
            "history"
          ]
        },
        "retrieval": {
          "top_lead_genre_limit": 6,
          "top_tag_limit": 10,
          "top_genre_limit": 8,
          "threshold_scale": 1.0,
          "numeric_thresholds": {
            "tempo": 20.0,
            "key": 2.0,
            "mode": 0.5,
            "duration_ms": 45000.0
          },
          "keep_rule": "keep if not seed and (semantic_score >= 2 or (semantic_score >= 1 and numeric_pass_count >= 1))"
        },
        "scoring": {
          "numeric_thresholds": {
            "tempo": 20.0,
            "key": 2.0,
            "mode": 0.5,
            "duration_ms": 45000.0
          },
          "component_weights": {
            "tempo": 0.2,
            "duration_ms": 0.13,
            "key": 0.13,
            "mode": 0.09,
            "lead_genre": 0.17,
            "genre_overlap": 0.12,
            "tag_overlap": 0.16
          },
          "weight_override_component": null,
          "raw_override_value": null
        },
        "assembly": {
          "target_size": 10,
          "min_score_threshold": 0.35,
          "max_per_genre": 4,
          "max_consecutive": 2
        }
      },
      "stable_hashes": {
        "profile_semantic_hash": "A384E4729FDB2357684870130F245F81913E50A98255E8D15A216BEE0F90FB59",
        "seed_trace_hash": "7896232795DF347E426EEE2F5346BAA1A776F445FEBCA08B95FAFF1B884A1C7E",
        "filtered_candidates_hash": "D160E6B2FE3E13BC9E0EB8D430A67580CAFEBBB82AE37BAB332928C32A25C0A5",
        "candidate_decisions_hash": "54E4F14F1BEFCA6163671CA121B94CEFF5AE0E1E43B2B4A176D195F46F025B24",
        "ranked_output_hash": "D0764BA430A44E797A6D02D5D3F1EB5D8D8FC3CF4CA22C21D4C2A6173D1835A8",
        "assembly_trace_hash": "0B2EF977EB376DB44353DD9B549EC74B4E0C50DDF2F19B4FEBA2CA1DD6E43201",
        "playlist_output_hash": "D16015CFA1AC70E93A22F798E713BC14C6ED27617B7715715429842CF312D038"
      },
      "metrics": {
        "selected_event_count": 1563,
        "matched_seed_count": 1563,
        "candidate_pool_size": 56691,
        "scored_candidate_count": 56691,
        "playlist_length": 10,
        "top10_track_ids": [
          "CaR8UnowNJUR5Dib",
          "yEz9rqTTulkiDDm7",
          "M3ApGs7RGZwXHqs4",
          "rqeIltq5ixzHA5EG",
          "s0Qo4gihN9Rzx8we",
          "qob8Z8qGt0UR4JAs",
          "Xh9f0R2Q7wJMaxhy",
          "HheoXQPQtBis2mmJ",
          "M1aGgogF0dGiRiXA",
          "YEWH2dMDiRCIJy7F"
        ],
        "playlist_track_ids": [
          "CaR8UnowNJUR5Dib",
          "yEz9rqTTulkiDDm7",
          "M3ApGs7RGZwXHqs4",
          "rqeIltq5ixzHA5EG",
          "s0Qo4gihN9Rzx8we",
          "qob8Z8qGt0UR4JAs",
          "Xh9f0R2Q7wJMaxhy",
          "HheoXQPQtBis2mmJ",
          "M1aGgogF0dGiRiXA",
          "CZOYJJKuyuUosACw"
        ],
        "dominant_lead_genres": [
          "pop",
          "classic rock",
          "rock",
          "progressive rock",
          "new wave"
        ],
        "dominant_tags": [
          "rock",
          "classic rock",
          "pop",
          "80s",
          "70s"
        ],
        "mean_component_contributions": {
          "tempo": 0.056181,
          "duration_ms": 0.030051,
          "key": 0.020326,
          "mode": 0.024535,
          "lead_genre": 0.045727,
          "genre_overlap": 0.027141,
          "tag_overlap": 0.03098
        },
        "playlist_genre_mix": {
          "classic rock": 4,
          "pop": 4,
          "rock": 2
        }
      },
      "comparison_to_baseline": {
        "observable_shift": true,
        "expected_direction_met": true,
        "candidate_pool_size_delta": 0,
        "playlist_length_delta": 0,
        "top10_overlap_count": 10,
        "top10_overlap_ratio": 1.0,
        "playlist_overlap_count": 10,
        "playlist_overlap_ratio": 1.0,
        "top10_added_track_ids": [],
        "top10_removed_track_ids": [],
        "playlist_added_track_ids": [],
        "playlist_removed_track_ids": [],
        "profile_lead_genres_before": [
          "pop",
          "classic rock",
          "rock",
          "progressive rock",
          "new wave"
        ],
        "profile_lead_genres_after": [
          "pop",
          "classic rock",
          "rock",
          "progressive rock",
          "new wave"
        ],
        "component_mean_delta": {
          "duration_ms": 0.0,
          "genre_overlap": 0.0,
          "key": 0.0,
          "lead_genre": 0.0,
          "mode": 0.0,
          "tag_overlap": 0.0,
          "tempo": 0.0
        },
        "rank_shift_summary": {
          "common_candidate_count": 56691,
          "mean_abs_rank_delta": 0.0,
          "max_rank_improvement": 0,
          "max_rank_drop": 0,
          "top_risers": [],
          "top_fallers": []
        }
      },
      "archive_dir": "07_implementation/implementation_notes/controllability/outputs/scenarios/no_influence_tracks"
    },
    {
      "scenario_id": "valence_weight_up",
      "test_id": "EP-CTRL-002",
      "control_surface": "feature_weight",
      "description": "Increase one score-component raw weight and renormalize all score weights to preserve a 1.0 total.",
      "expected_effect": "tracks with stronger fit on the boosted component should gain score contribution and rank position",
      "repeat_consistent": true,
      "config_hash": "4810451CE5753847049A86FE02002F9ED2BEB7E88FE9EF42E48F17EC17A0DCE2",
      "effective_config": {
        "scenario_id": "valence_weight_up",
        "test_id": "EP-CTRL-002",
        "control_surface": "feature_weight",
        "description": "Increase one score-component raw weight and renormalize all score weights to preserve a 1.0 total.",
        "expected_effect": "tracks with stronger fit on the boosted component should gain score contribution and rank position",
        "profile": {
          "effective_weight_rule": "effective_weight = preference_weight",
          "numeric_feature_columns": [
            "danceability",
            "energy",
            "valence",
            "tempo",
            "key",
            "mode",
            "popularity",
            "duration_ms"
          ],
          "top_tag_limit": 10,
          "top_genre_limit": 10,
          "top_lead_genre_limit": 10,
          "aggregation_rules": {
            "numeric": "weighted mean over numeric columns embedded in the BL-003 enriched seed table; key uses weighted circular mean on the 12-semitone wheel",
            "tags": "sum(preference_weight) over DS-001 tag labels",
            "genres": "sum(preference_weight) over DS-001 genre labels",
            "lead_genres": "sum(preference_weight)"
          },
          "include_interaction_types": [
            "history",
            "influence"
          ]
        },
        "retrieval": {
          "top_lead_genre_limit": 6,
          "top_tag_limit": 10,
          "top_genre_limit": 8,
          "threshold_scale": 1.0,
          "numeric_thresholds": {
            "tempo": 20.0,
            "key": 2.0,
            "mode": 0.5,
            "duration_ms": 45000.0
          },
          "keep_rule": "keep if not seed and (semantic_score >= 2 or (semantic_score >= 1 and numeric_pass_count >= 1))"
        },
        "scoring": {
          "numeric_thresholds": {
            "tempo": 20.0,
            "key": 2.0,
            "mode": 0.5,
            "duration_ms": 45000.0
          },
          "component_weights": {
            "tempo": 0.259259,
            "duration_ms": 0.12037,
            "key": 0.12037,
            "mode": 0.083333,
            "lead_genre": 0.157407,
            "genre_overlap": 0.111111,
            "tag_overlap": 0.148148
          },
          "weight_override_component": "tempo",
          "raw_override_value": 0.28
        },
        "assembly": {
          "target_size": 10,
          "min_score_threshold": 0.35,
          "max_per_genre": 4,
          "max_consecutive": 2
        }
      },
      "stable_hashes": {
        "profile_semantic_hash": "783BE37C440FAF30FC81CABB6605049DE088FBEC87A9FCE2840F64254B192372",
        "seed_trace_hash": "7896232795DF347E426EEE2F5346BAA1A776F445FEBCA08B95FAFF1B884A1C7E",
        "filtered_candidates_hash": "D160E6B2FE3E13BC9E0EB8D430A67580CAFEBBB82AE37BAB332928C32A25C0A5",
        "candidate_decisions_hash": "54E4F14F1BEFCA6163671CA121B94CEFF5AE0E1E43B2B4A176D195F46F025B24",
        "ranked_output_hash": "AF26F3AE0D942BA3C2C8D5696DC15266A1624CB3F73F9637C36E0CF643211504",
        "assembly_trace_hash": "97C423C039914756B71501CDEF9D841C7F4079A94E23445A4D0ECE4DD07C21B3",
        "playlist_output_hash": "EA54CC61782922061ABDB2295DA57ECE143DD830DFBAAC27A81587C9EB4B793F"
      },
      "metrics": {
        "selected_event_count": 1563,
        "matched_seed_count": 1563,
        "candidate_pool_size": 56691,
        "scored_candidate_count": 56691,
        "playlist_length": 10,
        "top10_track_ids": [
          "CaR8UnowNJUR5Dib",
          "yEz9rqTTulkiDDm7",
          "M3ApGs7RGZwXHqs4",
          "rqeIltq5ixzHA5EG",
          "s0Qo4gihN9Rzx8we",
          "Xh9f0R2Q7wJMaxhy",
          "HheoXQPQtBis2mmJ",
          "qob8Z8qGt0UR4JAs",
          "CZOYJJKuyuUosACw",
          "hU7yckCKoiTkHjwi"
        ],
        "playlist_track_ids": [
          "CaR8UnowNJUR5Dib",
          "yEz9rqTTulkiDDm7",
          "M3ApGs7RGZwXHqs4",
          "rqeIltq5ixzHA5EG",
          "s0Qo4gihN9Rzx8we",
          "Xh9f0R2Q7wJMaxhy",
          "HheoXQPQtBis2mmJ",
          "qob8Z8qGt0UR4JAs",
          "CZOYJJKuyuUosACw",
          "M1aGgogF0dGiRiXA"
        ],
        "dominant_lead_genres": [
          "pop",
          "classic rock",
          "rock",
          "progressive rock",
          "new wave"
        ],
        "dominant_tags": [
          "rock",
          "classic rock",
          "pop",
          "80s",
          "70s"
        ],
        "mean_component_contributions": {
          "tempo": 0.072827,
          "duration_ms": 0.027825,
          "key": 0.01882,
          "mode": 0.022717,
          "lead_genre": 0.04234,
          "genre_overlap": 0.025131,
          "tag_overlap": 0.028685
        },
        "playlist_genre_mix": {
          "classic rock": 4,
          "pop": 4,
          "rock": 2
        }
      },
      "comparison_to_baseline": {
        "observable_shift": true,
        "expected_direction_met": true,
        "candidate_pool_size_delta": 0,
        "playlist_length_delta": 0,
        "top10_overlap_count": 8,
        "top10_overlap_ratio": 0.8,
        "playlist_overlap_count": 10,
        "playlist_overlap_ratio": 1.0,
        "top10_added_track_ids": [
          "CZOYJJKuyuUosACw",
          "hU7yckCKoiTkHjwi"
        ],
        "top10_removed_track_ids": [
          "M1aGgogF0dGiRiXA",
          "YEWH2dMDiRCIJy7F"
        ],
        "playlist_added_track_ids": [],
        "playlist_removed_track_ids": [],
        "profile_lead_genres_before": [
          "pop",
          "classic rock",
          "rock",
          "progressive rock",
          "new wave"
        ],
        "profile_lead_genres_after": [
          "pop",
          "classic rock",
          "rock",
          "progressive rock",
          "new wave"
        ],
        "component_mean_delta": {
          "duration_ms": -0.002226,
          "genre_overlap": -0.00201,
          "key": -0.001506,
          "lead_genre": -0.003387,
          "mode": -0.001818,
          "tag_overlap": -0.002295,
          "tempo": 0.016646
        },
        "rank_shift_summary": {
          "common_candidate_count": 56691,
          "mean_abs_rank_delta": 2038.375,
          "max_rank_improvement": 8869,
          "max_rank_drop": -4277,
          "top_risers": [
            {
              "track_id": "CmikkFTB7vU3zn4y",
              "baseline_rank": 30368,
              "scenario_rank": 21499,
              "rank_delta": 8869
            },
            {
              "track_id": "7h9u5LFzbF7EMyKs",
              "baseline_rank": 31499,
              "scenario_rank": 22652,
              "rank_delta": 8847
            },
            {
              "track_id": "Vx7W1muqnFgFdmL4",
              "baseline_rank": 31480,
              "scenario_rank": 22634,
              "rank_delta": 8846
            },
            {
              "track_id": "RHWdyFgBS6PerWlM",
              "baseline_rank": 31883,
              "scenario_rank": 23069,
              "rank_delta": 8814
            },
            {
              "track_id": "Ms60PqwQCI5Is6wU",
              "baseline_rank": 31319,
              "scenario_rank": 22510,
              "rank_delta": 8809
            }
          ],
          "top_fallers": [
            {
              "track_id": "NM16q5EFCYh5vhaH",
              "baseline_rank": 15077,
              "scenario_rank": 19354,
              "rank_delta": -4277
            },
            {
              "track_id": "sBk4lV1M3O26HEqf",
              "baseline_rank": 15087,
              "scenario_rank": 19364,
              "rank_delta": -4277
            },
            {
              "track_id": "KGgXRGJbyjrRSiPV",
              "baseline_rank": 15083,
              "scenario_rank": 19358,
              "rank_delta": -4275
            },
            {
              "track_id": "KzJhZmSkyX6lFuSo",
              "baseline_rank": 15108,
              "scenario_rank": 19383,
              "rank_delta": -4275
            },
            {
              "track_id": "i2UuU4CiJoZM6pHa",
              "baseline_rank": 15868,
              "scenario_rank": 20143,
              "rank_delta": -4275
            }
          ]
        }
      },
      "archive_dir": "07_implementation/implementation_notes/controllability/outputs/scenarios/valence_weight_up"
    },
    {
      "scenario_id": "stricter_thresholds",
      "test_id": "EP-CTRL-003",
      "control_surface": "candidate_threshold",
      "description": "Tighten all numeric retrieval thresholds by multiplying them by 0.75.",
      "expected_effect": "candidate pool should shrink and playlist overlap should reduce or reorder",
      "repeat_consistent": true,
      "config_hash": "517F90B18165B6DD808D59D058F65498DF085AB1C8BCD640F126AB243C6B9846",
      "effective_config": {
        "scenario_id": "stricter_thresholds",
        "test_id": "EP-CTRL-003",
        "control_surface": "candidate_threshold",
        "description": "Tighten all numeric retrieval thresholds by multiplying them by 0.75.",
        "expected_effect": "candidate pool should shrink and playlist overlap should reduce or reorder",
        "profile": {
          "effective_weight_rule": "effective_weight = preference_weight",
          "numeric_feature_columns": [
            "danceability",
            "energy",
            "valence",
            "tempo",
            "key",
            "mode",
            "popularity",
            "duration_ms"
          ],
          "top_tag_limit": 10,
          "top_genre_limit": 10,
          "top_lead_genre_limit": 10,
          "aggregation_rules": {
            "numeric": "weighted mean over numeric columns embedded in the BL-003 enriched seed table; key uses weighted circular mean on the 12-semitone wheel",
            "tags": "sum(preference_weight) over DS-001 tag labels",
            "genres": "sum(preference_weight) over DS-001 genre labels",
            "lead_genres": "sum(preference_weight)"
          },
          "include_interaction_types": [
            "history",
            "influence"
          ]
        },
        "retrieval": {
          "top_lead_genre_limit": 6,
          "top_tag_limit": 10,
          "top_genre_limit": 8,
          "threshold_scale": 0.75,
          "numeric_thresholds": {
            "tempo": 15.0,
            "key": 1.5,
            "mode": 0.375,
            "duration_ms": 33750.0
          },
          "keep_rule": "keep if not seed and (semantic_score >= 2 or (semantic_score >= 1 and numeric_pass_count >= 1))"
        },
        "scoring": {
          "numeric_thresholds": {
            "tempo": 20.0,
            "key": 2.0,
            "mode": 0.5,
            "duration_ms": 45000.0
          },
          "component_weights": {
            "tempo": 0.2,
            "duration_ms": 0.13,
            "key": 0.13,
            "mode": 0.09,
            "lead_genre": 0.17,
            "genre_overlap": 0.12,
            "tag_overlap": 0.16
          },
          "weight_override_component": null,
          "raw_override_value": null
        },
        "assembly": {
          "target_size": 10,
          "min_score_threshold": 0.35,
          "max_per_genre": 4,
          "max_consecutive": 2
        }
      },
      "stable_hashes": {
        "profile_semantic_hash": "783BE37C440FAF30FC81CABB6605049DE088FBEC87A9FCE2840F64254B192372",
        "seed_trace_hash": "7896232795DF347E426EEE2F5346BAA1A776F445FEBCA08B95FAFF1B884A1C7E",
        "filtered_candidates_hash": "089FDE0122C9943E4011EA72554F5F41F6D0338349CC315C3751651422219EFA",
        "candidate_decisions_hash": "5B63B23A137494D6CAB109EED08AA405726DF4CCF1A5F9C062F32A489A079795",
        "ranked_output_hash": "35B8EC889DC45045FF2D4B32F3BFEDE7465BC9B872BE4F0A20E44C7C8F1D40F7",
        "assembly_trace_hash": "4802D0B589E02B5A649C6E798503B3C7A009CE5CCDD434B6826C67C1F42B4BEB",
        "playlist_output_hash": "D16015CFA1AC70E93A22F798E713BC14C6ED27617B7715715429842CF312D038"
      },
      "metrics": {
        "selected_event_count": 1563,
        "matched_seed_count": 1563,
        "candidate_pool_size": 56342,
        "scored_candidate_count": 56342,
        "playlist_length": 10,
        "top10_track_ids": [
          "CaR8UnowNJUR5Dib",
          "yEz9rqTTulkiDDm7",
          "M3ApGs7RGZwXHqs4",
          "rqeIltq5ixzHA5EG",
          "s0Qo4gihN9Rzx8we",
          "qob8Z8qGt0UR4JAs",
          "Xh9f0R2Q7wJMaxhy",
          "HheoXQPQtBis2mmJ",
          "M1aGgogF0dGiRiXA",
          "YEWH2dMDiRCIJy7F"
        ],
        "playlist_track_ids": [
          "CaR8UnowNJUR5Dib",
          "yEz9rqTTulkiDDm7",
          "M3ApGs7RGZwXHqs4",
          "rqeIltq5ixzHA5EG",
          "s0Qo4gihN9Rzx8we",
          "qob8Z8qGt0UR4JAs",
          "Xh9f0R2Q7wJMaxhy",
          "HheoXQPQtBis2mmJ",
          "M1aGgogF0dGiRiXA",
          "CZOYJJKuyuUosACw"
        ],
        "dominant_lead_genres": [
          "pop",
          "classic rock",
          "rock",
          "progressive rock",
          "new wave"
        ],
        "dominant_tags": [
          "rock",
          "classic rock",
          "pop",
          "80s",
          "70s"
        ],
        "mean_component_contributions": {
          "tempo": 0.056444,
          "duration_ms": 0.030192,
          "key": 0.020448,
          "mode": 0.024687,
          "lead_genre": 0.046,
          "genre_overlap": 0.027301,
          "tag_overlap": 0.031143
        },
        "playlist_genre_mix": {
          "classic rock": 4,
          "pop": 4,
          "rock": 2
        }
      },
      "comparison_to_baseline": {
        "observable_shift": true,
        "expected_direction_met": true,
        "candidate_pool_size_delta": -349,
        "playlist_length_delta": 0,
        "top10_overlap_count": 10,
        "top10_overlap_ratio": 1.0,
        "playlist_overlap_count": 10,
        "playlist_overlap_ratio": 1.0,
        "top10_added_track_ids": [],
        "top10_removed_track_ids": [],
        "playlist_added_track_ids": [],
        "playlist_removed_track_ids": [],
        "profile_lead_genres_before": [
          "pop",
          "classic rock",
          "rock",
          "progressive rock",
          "new wave"
        ],
        "profile_lead_genres_after": [
          "pop",
          "classic rock",
          "rock",
          "progressive rock",
          "new wave"
        ],
        "component_mean_delta": {
          "duration_ms": 0.000141,
          "genre_overlap": 0.00016,
          "key": 0.000122,
          "lead_genre": 0.000273,
          "mode": 0.000152,
          "tag_overlap": 0.000163,
          "tempo": 0.000263
        },
        "rank_shift_summary": {
          "common_candidate_count": 56342,
          "mean_abs_rank_delta": 4.946,
          "max_rank_improvement": 316,
          "max_rank_drop": 0,
          "top_risers": [
            {
              "track_id": "07JhtfVVlSifEGu6",
              "baseline_rank": 56601,
              "scenario_rank": 56285,
              "rank_delta": 316
            },
            {
              "track_id": "0BOfpnljgDlsgqz6",
              "baseline_rank": 56602,
              "scenario_rank": 56286,
              "rank_delta": 316
            },
            {
              "track_id": "12J0SifUY3ZcE7dL",
              "baseline_rank": 56603,
              "scenario_rank": 56287,
              "rank_delta": 316
            },
            {
              "track_id": "1yD7beXgdNjMQCsJ",
              "baseline_rank": 56604,
              "scenario_rank": 56288,
              "rank_delta": 316
            },
            {
              "track_id": "22JDgutxkjEvsRIv",
              "baseline_rank": 56605,
              "scenario_rank": 56289,
              "rank_delta": 316
            }
          ],
          "top_fallers": []
        }
      },
      "archive_dir": "07_implementation/implementation_notes/controllability/outputs/scenarios/stricter_thresholds"
    },
    {
      "scenario_id": "looser_thresholds",
      "test_id": "EP-CTRL-003",
      "control_surface": "candidate_threshold",
      "description": "Loosen all numeric retrieval thresholds by multiplying them by 1.25.",
      "expected_effect": "candidate pool should expand and downstream ranking or playlist composition should change",
      "repeat_consistent": true,
      "config_hash": "BD599197DB48171259840803383488BADDF12B31F468BBFC6B2E475322BB5D29",
      "effective_config": {
        "scenario_id": "looser_thresholds",
        "test_id": "EP-CTRL-003",
        "control_surface": "candidate_threshold",
        "description": "Loosen all numeric retrieval thresholds by multiplying them by 1.25.",
        "expected_effect": "candidate pool should expand and downstream ranking or playlist composition should change",
        "profile": {
          "effective_weight_rule": "effective_weight = preference_weight",
          "numeric_feature_columns": [
            "danceability",
            "energy",
            "valence",
            "tempo",
            "key",
            "mode",
            "popularity",
            "duration_ms"
          ],
          "top_tag_limit": 10,
          "top_genre_limit": 10,
          "top_lead_genre_limit": 10,
          "aggregation_rules": {
            "numeric": "weighted mean over numeric columns embedded in the BL-003 enriched seed table; key uses weighted circular mean on the 12-semitone wheel",
            "tags": "sum(preference_weight) over DS-001 tag labels",
            "genres": "sum(preference_weight) over DS-001 genre labels",
            "lead_genres": "sum(preference_weight)"
          },
          "include_interaction_types": [
            "history",
            "influence"
          ]
        },
        "retrieval": {
          "top_lead_genre_limit": 6,
          "top_tag_limit": 10,
          "top_genre_limit": 8,
          "threshold_scale": 1.25,
          "numeric_thresholds": {
            "tempo": 25.0,
            "key": 2.5,
            "mode": 0.625,
            "duration_ms": 56250.0
          },
          "keep_rule": "keep if not seed and (semantic_score >= 2 or (semantic_score >= 1 and numeric_pass_count >= 1))"
        },
        "scoring": {
          "numeric_thresholds": {
            "tempo": 20.0,
            "key": 2.0,
            "mode": 0.5,
            "duration_ms": 45000.0
          },
          "component_weights": {
            "tempo": 0.2,
            "duration_ms": 0.13,
            "key": 0.13,
            "mode": 0.09,
            "lead_genre": 0.17,
            "genre_overlap": 0.12,
            "tag_overlap": 0.16
          },
          "weight_override_component": null,
          "raw_override_value": null
        },
        "assembly": {
          "target_size": 10,
          "min_score_threshold": 0.35,
          "max_per_genre": 4,
          "max_consecutive": 2
        }
      },
      "stable_hashes": {
        "profile_semantic_hash": "783BE37C440FAF30FC81CABB6605049DE088FBEC87A9FCE2840F64254B192372",
        "seed_trace_hash": "7896232795DF347E426EEE2F5346BAA1A776F445FEBCA08B95FAFF1B884A1C7E",
        "filtered_candidates_hash": "2F6F584E476CC837A9E426C3632F8CC929C46750E9F171AE87620E4B52DDC13B",
        "candidate_decisions_hash": "5E0A6513903D2BB14D95B0B317C0491C57AB261B69FE6D255341911A0FAF378D",
        "ranked_output_hash": "49191C76B0B54E7838AF2D70159F7E4AE85957AB25359A79F8BC6034E4109141",
        "assembly_trace_hash": "7BACA72981785DA0FF1F8B4D4465CC5B3CF0F8CB9DBC8669A7CB0C7EA6739B64",
        "playlist_output_hash": "D16015CFA1AC70E93A22F798E713BC14C6ED27617B7715715429842CF312D038"
      },
      "metrics": {
        "selected_event_count": 1563,
        "matched_seed_count": 1563,
        "candidate_pool_size": 56946,
        "scored_candidate_count": 56946,
        "playlist_length": 10,
        "top10_track_ids": [
          "CaR8UnowNJUR5Dib",
          "yEz9rqTTulkiDDm7",
          "M3ApGs7RGZwXHqs4",
          "rqeIltq5ixzHA5EG",
          "s0Qo4gihN9Rzx8we",
          "qob8Z8qGt0UR4JAs",
          "Xh9f0R2Q7wJMaxhy",
          "HheoXQPQtBis2mmJ",
          "M1aGgogF0dGiRiXA",
          "YEWH2dMDiRCIJy7F"
        ],
        "playlist_track_ids": [
          "CaR8UnowNJUR5Dib",
          "yEz9rqTTulkiDDm7",
          "M3ApGs7RGZwXHqs4",
          "rqeIltq5ixzHA5EG",
          "s0Qo4gihN9Rzx8we",
          "qob8Z8qGt0UR4JAs",
          "Xh9f0R2Q7wJMaxhy",
          "HheoXQPQtBis2mmJ",
          "M1aGgogF0dGiRiXA",
          "CZOYJJKuyuUosACw"
        ],
        "dominant_lead_genres": [
          "pop",
          "classic rock",
          "rock",
          "progressive rock",
          "new wave"
        ],
        "dominant_tags": [
          "rock",
          "classic rock",
          "pop",
          "80s",
          "70s"
        ],
        "mean_component_contributions": {
          "tempo": 0.055929,
          "duration_ms": 0.029916,
          "key": 0.020235,
          "mode": 0.024425,
          "lead_genre": 0.04553,
          "genre_overlap": 0.027027,
          "tag_overlap": 0.030859
        },
        "playlist_genre_mix": {
          "classic rock": 4,
          "pop": 4,
          "rock": 2
        }
      },
      "comparison_to_baseline": {
        "observable_shift": true,
        "expected_direction_met": true,
        "candidate_pool_size_delta": 255,
        "playlist_length_delta": 0,
        "top10_overlap_count": 10,
        "top10_overlap_ratio": 1.0,
        "playlist_overlap_count": 10,
        "playlist_overlap_ratio": 1.0,
        "top10_added_track_ids": [],
        "top10_removed_track_ids": [],
        "playlist_added_track_ids": [],
        "playlist_removed_track_ids": [],
        "profile_lead_genres_before": [
          "pop",
          "classic rock",
          "rock",
          "progressive rock",
          "new wave"
        ],
        "profile_lead_genres_after": [
          "pop",
          "classic rock",
          "rock",
          "progressive rock",
          "new wave"
        ],
        "component_mean_delta": {
          "duration_ms": -0.000135,
          "genre_overlap": -0.000114,
          "key": -9.1e-05,
          "lead_genre": -0.000197,
          "mode": -0.00011,
          "tag_overlap": -0.000121,
          "tempo": -0.000252
        },
        "rank_shift_summary": {
          "common_candidate_count": 56691,
          "mean_abs_rank_delta": 0.286,
          "max_rank_improvement": 0,
          "max_rank_drop": -187,
          "top_risers": [],
          "top_fallers": [
            {
              "track_id": "9DwxP2q95xUhHUGM",
              "baseline_rank": 56689,
              "scenario_rank": 56876,
              "rank_delta": -187
            },
            {
              "track_id": "VtwdxlksohvZrAFT",
              "baseline_rank": 56687,
              "scenario_rank": 56874,
              "rank_delta": -187
            },
            {
              "track_id": "ZUAd05n8T6RWYE7V",
              "baseline_rank": 56690,
              "scenario_rank": 56877,
              "rank_delta": -187
            },
            {
              "track_id": "pYXsKZTi6rXoYNeM",
              "baseline_rank": 56691,
              "scenario_rank": 56878,
              "rank_delta": -187
            },
            {
              "track_id": "xoDWi8UhtqT0zdcJ",
              "baseline_rank": 56688,
              "scenario_rank": 56875,
              "rank_delta": -187
            }
          ]
        }
      },
      "archive_dir": "07_implementation/implementation_notes/controllability/outputs/scenarios/looser_thresholds"
    }
  ],
  "results": {
    "all_scenarios_repeat_consistent": true,
    "all_variant_shifts_observable": true,
    "all_variant_directions_met": true,
    "status": "pass"
  },
  "output_artifacts": {
    "config_snapshot_path": "07_implementation/implementation_notes/controllability/outputs/bl011_controllability_config_snapshot.json",
    "run_matrix_path": "07_implementation/implementation_notes/controllability/outputs/bl011_controllability_run_matrix.csv",
    "scenario_dirs": [
      "07_implementation/implementation_notes/controllability/outputs/scenarios/baseline",
      "07_implementation/implementation_notes/controllability/outputs/scenarios/no_influence_tracks",
      "07_implementation/implementation_notes/controllability/outputs/scenarios/valence_weight_up",
      "07_implementation/implementation_notes/controllability/outputs/scenarios/stricter_thresholds",
      "07_implementation/implementation_notes/controllability/outputs/scenarios/looser_thresholds"
    ]
  }
}
